qsp/tsp.py
qsp/adiabatic/__init__.py
qsp/adiabatic/adiabatic_1d.py
qsp/adiabatic/adiabatic_2d.py
qsp/lcu/__init__.py
qsp/lcu/lcu.py
qsp/lcu/lcu_optimization_manopt.py
qsp/lcu/lcu_optimization_misc.py
qsp/lcu/lcu_optimization_qgopt.py
qsp/misc_states/__init__.py
qsp/misc_states/misc_tns.py
qsp/q_circs/__init__.py
qsp/q_circs/qiskit_circuit.py
qsp/q_circs/qiskit_lcu_circuit.py
qsp/qsp_helper_routines/qsp_helper_routines.py
qsp/sequential/__init__.py
qsp/sequential/core.py
qsp/sequential/qctn.py
qsp/sequential/sequential.py
qsp/sequential/sequential_optimization.py
qsp/tsp_helper_routines/__init__.py
qsp/tsp_helper_routines/helper_routines.py
qsp-0.0.5.dist-info/LICENSE.txt
qsp-0.0.5.dist-info/METADATA
qsp-0.0.5.dist-info/WHEEL
qsp-0.0.5.dist-info/top_level.txt
qsp-0.0.5.dist-info/RECORD
