Metadata-Version: 2.1
Name: qsp
Version: 0.0.5
Summary: implementation of different methods to prepare quantum states on quantum computer
Home-page: https://github.com/mohsin-0/qsp
Author: Mohsin Iqbal
Author-email: mohsin.iqbal@cambridgequantum.com
License: Apache License 2.0
Keywords: quantum state preparation tensor networks
Classifier: Development Status :: 4 - Beta
Classifier: Intended Audience :: Science/Research
Classifier: License :: OSI Approved :: Apache Software License
Classifier: Programming Language :: Python :: 3.9
Classifier: Programming Language :: Python :: 3.10
Classifier: Topic :: Scientific/Engineering :: Physics
Requires-Python: >=3.9
License-File: LICENSE.txt
Requires-Dist: ncon
Requires-Dist: qiskit-aer (==0.11.2)
Requires-Dist: qiskit-terra (>=0.25.1)
Requires-Dist: quimb
Requires-Dist: tensornetwork
Requires-Dist: tensorflow
Requires-Dist: pymanopt
Requires-Dist: QGOpt
